m3u8/__init__.py
m3u8/httpclient.py
m3u8/mixins.py
m3u8/model.py
m3u8/parser.py
m3u8/protocol.py
rlaphoenix.m3u8-3.4.0.dist-info/LICENSE
rlaphoenix.m3u8-3.4.0.dist-info/METADATA
rlaphoenix.m3u8-3.4.0.dist-info/WHEEL
rlaphoenix.m3u8-3.4.0.dist-info/top_level.txt
rlaphoenix.m3u8-3.4.0.dist-info/RECORD
