Metadata-Version: 2.1
Name: rlaphoenix.m3u8
Version: 3.4.0
Summary: Python m3u8 parser
Home-page: https://github.com/globocom/m3u8
Author: Globo.com
License: MIT
Requires-Python: >=3.6
License-File: LICENSE
Requires-Dist: iso8601
